pydevd_reload.py
pydevd_reload-1.2.dist-info/DESCRIPTION.rst
pydevd_reload-1.2.dist-info/METADATA
pydevd_reload-1.2.dist-info/RECORD
pydevd_reload-1.2.dist-info/WHEEL
pydevd_reload-1.2.dist-info/metadata.json
pydevd_reload-1.2.dist-info/top_level.txt
