Metadata-Version: 2.0
Name: pydevd-reload
Version: 1.2
Summary: An enhanced reload module from PyDev
Home-page: https://github.com/fyrestone/pydevd_reload
Author: fyrestone
Author-email: fyrestone@outlook.com
License: Eclipse Public License
Keywords: reload generic utility
Platform: All
Classifier: Development Status :: 5 - Production/Stable
Classifier: Intended Audience :: Developers
Classifier: License :: OSI Approved :: Eclipse Public License 1.0 (EPL-1.0)
Classifier: Natural Language :: English
Classifier: Operating System :: OS Independent
Classifier: Programming Language :: Python :: 2
Classifier: Programming Language :: Python :: 3
Classifier: Topic :: Software Development :: Libraries
Classifier: Topic :: Utilities
